{
  "id": "127",
  "artist": "eunlo",
  "title": "I Need You",
  "year": "2025",
  "album": "Pump Up the Healthy Love OST Part. 3",
  "genre": "Soundtrack",
  "category": "K-Pop",
  "duration": "03:33",
  "size": "5.05 MB",
  "size128": "",
  "size192": "",
  "size320": "",
  "bitrate": "192",
  "bitrate128": "",
  "bitrate192": "",
  "bitrate320": "",
  "thumb": "https://cdn.jsdelivr.net/gh/caraaink/meownime@1125230cc2f1fb6cf40debafe2e5dd9c40950414/cover/soundtrack/eunlo_I_Need_You.jpg",
  "link": "https://metrolagu.wapkiz.mobi/filedownload/3025711/Eunlo-I-Need-You.mp3",
  "link2": "https://drive.google.com/file/d/1pRFDp0l5ysonLIUDAcy7PbqUGdAi4zaY/view?usp=drivesdk",
  "url128": "",
  "url192": "",
  "url320": "",
  "lyricstimestamp": "",
  "lyrics": "<center><b> Lyric eunlo - I Need You </b> <br> <br>  <b>[Romanization]</b> <br><br>Every time I think of you, all day and night<br> anywhere', anywhere'<br> Every time I think of you, even in dreams<br> anywhere', anywhere'<br> <br> When I was lost, you held my hand<br> and now I want to be the light<br> In the dark<br> <br> I'm dreaming of us<br> dreaming of us<br> dreaming of us<br> here together<br> <br> I'm dreaming of us<br> dreaming of us here together<br> forever<br> I'll stay with you<br> <br> every time I see you, stars light up the sky<br> anywhere', anywhere'<br> <br> When I was lost, you found my way<br> And now I'll be your shining star<br> in your heart<br> <br> I'm dreaming of us<br> dreaming of us<br> dreaming of us<br> here together<br> <br> I'm dreaming of us<br> dreaming of us here together<br> forever<br> I'll stay with you<br> <br> I'll always be with you<br> Even if you don't know how I feel about you<br> I'm waiting here for you<br> <br> No matter what, I'll stay<br> I'll never let you go<br> And you will feel the love I give to you<br> <br> I'm dreaming of us<br> dreaming of us<br> dreaming of us<br> here together<br> <br> I'm dreaming of us<br> dreaming of us here together<br> forever<br> <br> I'll stay with you<br> I'll always be with you<br><br> <b>[Hangeul]</b> <br><br>Every time I think of you, all day and night<br><br>anywhere', anywhere'<br><br>Every time I think of you, even in dreams<br><br>anywhere', anywhere'<br><br><br><br>When I was lost, you held my hand<br><br>and now I want to be the light<br><br>In the dark<br><br><br><br>I'm dreaming of us<br><br>dreaming of us<br><br>dreaming of us<br><br>here together<br><br><br><br>I'm dreaming of us<br><br>dreaming of us here together<br><br>forever<br><br>I'll stay with you<br><br><br><br>every time I see you, stars light up the sky<br><br>anywhere', anywhere'<br><br><br><br>When I was lost, you found my way<br><br>And now I'll be your shining star<br><br>in your heart<br><br><br><br>I'm dreaming of us<br><br>dreaming of us<br><br>dreaming of us<br><br>here together<br><br><br><br>I'm dreaming of us<br><br>dreaming of us here together<br><br>forever<br><br>I'll stay with you<br><br><br><br>I'll always be with you<br><br>Even if you don't know how I feel about you<br><br>I'm waiting here for you<br><br><br><br>No matter what, I'll stay<br><br>I'll never let you go<br><br>And you will feel the love I give to you<br><br><br><br>I'm dreaming of us<br><br>dreaming of us<br><br>dreaming of us<br><br>here together<br><br><br><br>I'm dreaming of us<br><br>dreaming of us here together<br><br>forever<br><br><br><br>I'll stay with you<br><br>I'll always be with you</center>",
  "name": "eunlo - I Need You",
  "created_at": "2025-06-19T12:49:30.923Z",
  "hits": "2"
}