{
  "id": "237",
  "artist": "Park Gi Pyo",
  "title": "TO. J (Feat. Jihogivenchy)",
  "year": "2025",
  "album": "Nostalgia",
  "genre": "Rap",
  "category": "K-Pop",
  "duration": "03:14",
  "size": "4.55 MB",
  "size128": "",
  "size192": "",
  "size320": "",
  "bitrate": "192",
  "bitrate128": "",
  "bitrate192": "",
  "bitrate320": "",
  "thumb": "https://cdn.jsdelivr.net/gh/caraaink/meownime@16155f90d07c8aa3491fc54ef22c39881ea0c9c0/cover/rap/Park_Gi_Pyo_TO_J_Feat_Jihogivenchy.jpg",
  "link": "https://metrolagu.wapkiz.mobi/filedownload/3026204/Park-Gi-Pyo-TO-J-Feat-Jihogivenchy.mp3",
  "link2": "https://drive.google.com/file/d/1SPanqzTrjSa895DS2NfGt_Y8dYbHsvTc/view?usp=drivesdk",
  "url128": "",
  "url192": "",
  "url320": "",
  "lyricstimestamp": "",
  "lyrics": "<center><b> Lyric Park Gi Pyo - TO. J (Feat. Jihogivenchy) </b> <br> <br>  <b>[Romanization]</b> <br><br>Good Morning 'J'<br> tteonagan siganeun neomu ppareuge<br> neoui yaegireul deutgo isseo, yeojeonhi i jarine<br> chingguwa nanwotdeon daehwa, TVsok Rapper<br> i eopgyeeseo bitnaneun byeol, urin gateun chaepteo<br> <br> 20nyeoneul neowa hanggilman bomyeo georeosseo<br> gakkeum deunneun sosige nan siganui byeogeul neomeosseo<br> myeot il dwi nemoseupbomyeon eotteon mareul geonnaelkka<br> uriui siganeun dareugetji, gatdamyeon geugeon geojimmal<br> <br> kkum gatdeon gangnam, hyeonsilgwa kkumeul bakkwobeoryeosseo<br> 20segi sonyeonggati eorin sijeol neowa gati<br> Bibleeul jeogeonaga malloman haetdeon iyagi<br> dasi bol nareul gidaryeo,<br> meolgeman neukkin mujigaega fade out<br> <br> Let me talk about truly night<br> eoduwo boyeodo gureumi jina<br> neowa yaksokhaetdeon geu nari boyeo<br> dareuji aneul gieogirago mideo<br> J J Good morning J<br> J J Good morning J<br> J J Good morning J<br> J J Good morning J<br> <br> <br> Gq, I Miss you bro I miss you bro <br> How you have been? <br> How you have been,<br> always Look a don’t ever look Down man, <br> Only had a 6 Hour now <br> Now I am back in this shit right <br> I got all the powers and a wa, wa, wa <br> Yea, yea, I got all the powers and a wa, wa,<br> Got a stay up, Don’t ever look down look up<br> wiman bwa wiman bwa <br> mite bojima bojima, <br> I miss you bro, how you have been <br> I am doing all good, Hey <br> Make a million, make a billion <br> We are right Colleagues yea <br> We are riding Double RR<br> How you doing 24 Karrot <br> Cartier Bracelet LA.,<br> <br> ije gibuni eottae<br> byeonhaebeorin gonggireul neukkyeo pyeonhage relax<br> apeuro jueojin sigani urin mankie<br> dasi igyeonaelgeoya neoneun gwageoneun reset<br> <br> Let me talk about truly night<br> eoduwo boyeodo gureumi jina<br> neowa yaksokhaetdeon geu nari boyeo<br> dareuji aneul gieogirago mideo<br> J J Good morning J<br> J J Good morning J<br> J J Good morning J<br> J J Good morning J<br><br> <b>[Hangeul]</b> <br><br>Good Morning 'J'<br><br>떠나간 시간은 너무 빠르게<br><br>너의 얘기를 듣고 있어, 여전히 이 자리네<br><br>친구와 나눴던 대화, TV속 Rapper<br><br>이 업계에서 빛나는 별, 우린 같은 챕터<br><br><br><br>20년을 너와 한길만 보며 걸었어<br><br>가끔 듣는 소식에 난 시간의 벽을 넘었어<br><br>몇 일 뒤 네모습보면 어떤 말을 건낼까<br><br>우리의 시간은 다르겠지, 같다면 그건 거짓말<br><br><br><br>꿈 같던 강남, 현실과 꿈을 바꿔버렸어<br><br>20세기 소년같이 어린 시절 너와 같이<br><br>Bible을 적어나가 말로만 했던 이야기<br><br>다시 볼 날을 기다려,<br><br>멀게만 느낀 무지개가 fade out<br><br><br><br>Let me talk about truly night<br><br>어두워 보여도 구름이 지나<br><br>너와 약속했던 그 날이 보여<br><br>다르지 않을 기억이라고 믿어<br><br>J J Good morning J<br><br>J J Good morning J<br><br>J J Good morning J<br><br>J J Good morning J<br><br><br><br><br><br>Gq, I Miss you bro I miss you bro <br><br>How you have been? <br><br>How you have been,<br><br>always Look a don’t ever look Down man, <br><br>Only had a 6 Hour now <br><br>Now I am back in this shit right <br><br>I got all the powers and a wa, wa, wa <br><br>Yea, yea, I got all the powers and a wa, wa,<br><br>Got a stay up, Don’t ever look down look up<br><br>위만 봐 위만 봐 <br><br>밑에 보지마 보지마, <br><br>I miss you bro, how you have been <br><br>I am doing all good, Hey <br><br>Make a million, make a billion <br><br>We are right Colleagues yea <br><br>We are riding Double RR<br><br>How you doing 24 Karrot <br><br>Cartier Bracelet LA.,<br><br><br><br>이제 기분이 어때<br><br>변해버린 공기를 느껴 편하게 relax<br><br>앞으로 주어진 시간이 우린 많기에<br><br>다시 이겨낼거야 너는 과거는 reset<br><br><br><br>Let me talk about truly night<br><br>어두워 보여도 구름이 지나<br><br>너와 약속했던 그 날이 보여<br><br>다르지 않을 기억이라고 믿어<br><br>J J Good morning J<br><br>J J Good morning J<br><br>J J Good morning J<br><br>J J Good morning J</center>",
  "name": "Park Gi Pyo - TO. J (Feat. Jihogivenchy)",
  "created_at": "2025-06-20T00:48:55.734Z",
  "hits": "3"
}