{
  "id": "241",
  "artist": "Kim Hye Rim",
  "title": "F5",
  "year": "2025",
  "album": "reFresh",
  "genre": "Ballad",
  "category": "K-Pop",
  "duration": "03:04",
  "size": "4.36 MB",
  "size128": "",
  "size192": "",
  "size320": "",
  "bitrate": "192",
  "bitrate128": "",
  "bitrate192": "",
  "bitrate320": "",
  "thumb": "https://cdn.jsdelivr.net/gh/caraaink/meownime@cb92c0756eee92b800d2a78eeae4a8952da4ae60/cover/ballad/Kim_Hye_Rim_F5.jpg",
  "link": "https://metrolagu.wapkiz.mobi/filedownload/3026200/Kim-Hye-Rim-F5.mp3",
  "link2": "https://drive.google.com/file/d/1tyc799tWqAt_bEcSv9p6l1VJASLNlHPm/view?usp=drivesdk",
  "url128": "",
  "url192": "",
  "url320": "",
  "lyricstimestamp": "",
  "lyrics": "<center><b> Lyric Kim Hye Rim - F5 </b> <br> <br>  <b>[Romanization]</b> <br><br>ijeobeoryeosseo jigeumui nan<br> seoro jugobatdeon numbicheul<br> da ijeosseo geuttaeui neol<br> gyeolguk kkeutnabeoryeosseo<br> <br> ssodanaen geuttae nae mami<br> meonjicheoreom sarajyeo<br> da ijeosseo geuttae uri<br> yeongwonhal geot gatdeon geojitdo<br> <br> jigyeopgedo gipge paein<br> seulpeun sangcheoga jjijeobeorin geon<br> apeun gieokkajido <br> naege modu ppaeseoga nal utge hae<br> <br> dasi fly high neoui gwansim ttawin gidariji aneulge <br> aesseo ppajyeonaon geu jioge doragaji aneulge<br> ijeya bichi boin<br> ijeya nummuri gaein<br> deoreoun geu gieogeun<br> dasi tteoolliji aneulge<br> <br> jiwobeorilge geunarui neol<br> chagawotdeon neoui numbicheul<br> da jiulge eojeui neol<br> ijen kkeutnaebeorilge<br> <br> peobueun geuttae nae mami<br> jidokhi antakkawo<br> da kkeutnaellae ije uri<br> sseuldeeomneun mal deo an halge<br> <br> <br> aseulhage witaeropdeon<br> jinan sarangi jjijeobeorin geon<br> jichin gieokkajido<br> nega dasi gajyeoga nal utge hae<br> <br> dasi fly high neoui gwansim ttawin gidariji aneulge <br> aesseo ppajyeonaon geu jioge doragaji aneulge<br> ijeya bichi boin<br> ijeya nummuri gaein<br> deoreoun geu gieogeun<br> dasi tteoolliji aneulge<br> <br> naega neukkin i gotongui <br> cheomman bunui ilman neukkyeobwa<br> geu chagaun chueok soge<br> oeropge beotyeoga bwa<br> <br> jiwobeoryeosseo jigeumui nan<br> seoro jugobatdeon numbicheul<br> da ijeosseo geuttaeui neol<br> gyeolguk kkeutnabeoryeosseo<br> <br> ije fly high neoui miryeon ttawin chyeodaboji aneulge <br> gyeou domangchyeoon geu jiogeun doraboji aneulge<br> ijeya bichi boin<br> gansinhi nummuri gaein<br> deoreoun geu gieogeun<br> dasin tteoolliji aneulge<br> <br><br> <b>[Hangeul]</b> <br><br>잊어버렸어 지금의 난<br><br>서로 주고받던 눈빛을<br><br>다 잊었어 그때의 널<br><br>결국 끝나버렸어<br><br><br><br>쏟아낸 그때 내 맘이<br><br>먼지처럼 사라져<br><br>다 잊었어 그때 우리<br><br>영원할 것 같던 거짓도<br><br><br><br>지겹게도 깊게 패인<br><br>슬픈 상처가 찢어버린 건<br><br>아픈 기억까지도 <br><br>내게 모두 뺏어가 날 웃게 해<br><br><br><br>다시 fly high 너의 관심 따윈 기다리지 않을게 <br><br>애써 빠져나온 그 지옥에 돌아가지 않을게<br><br>이제야 빛이 보인<br><br>이제야 눈물이 개인<br><br>더러운 그 기억은<br><br>다시 떠올리지 않을게<br><br><br><br>지워버릴게 그날의 널<br><br>차가웠던 너의 눈빛을<br><br>다 지울게 어제의 널<br><br>이젠 끝내버릴게<br><br><br><br>퍼부은 그때 내 맘이<br><br>지독히 안타까워<br><br>다 끝낼래 이제 우리<br><br>쓸데없는 말 더 안 할게<br><br><br><br><br><br>아슬하게 위태롭던<br><br>지난 사랑이 찢어버린 건<br><br>지친 기억까지도<br><br>네가 다시 가져가 날 웃게 해<br><br><br><br>다시 fly high 너의 관심 따윈 기다리지 않을게 <br><br>애써 빠져나온 그 지옥에 돌아가지 않을게<br><br>이제야 빛이 보인<br><br>이제야 눈물이 개인<br><br>더러운 그 기억은<br><br>다시 떠올리지 않을게<br><br><br><br>내가 느낀 이 고통의 <br><br>천만 분의 일만 느껴봐<br><br>그 차가운 추억 속에<br><br>외롭게 버텨가 봐<br><br><br><br>지워버렸어 지금의 난<br><br>서로 주고받던 눈빛을<br><br>다 잊었어 그때의 널<br><br>결국 끝나버렸어<br><br><br><br>이제 fly high 너의 미련 따윈 쳐다보지 않을게 <br><br>겨우 도망쳐온 그 지옥은 돌아보지 않을게<br><br>이제야 빛이 보인<br><br>간신히 눈물이 개인<br><br>더러운 그 기억은<br><br>다신 떠올리지 않을게<br><br></center>",
  "name": "Kim Hye Rim - F5",
  "created_at": "2025-06-20T00:49:00.597Z",
  "hits": "5"
}